routexplorer/__init__.py
routexplorer/algorithms/Algorithm.py
routexplorer/algorithms/BruteForceSearch.py
routexplorer/algorithms/__init__.py
routexplorer/utils/Graph.py
routexplorer/utils/Utils.py
routexplorer/utils/__init__.py
routexplorer/utils/input_reader.py
routexplorer-0.0.5.dist-info/LICENSE.md
routexplorer-0.0.5.dist-info/METADATA
routexplorer-0.0.5.dist-info/WHEEL
routexplorer-0.0.5.dist-info/RECORD
