Metadata-Version: 2.1
Name: routexplorer
Version: 0.0.5
Summary: RouteXplorer is a lib developed to optimize routes in Complete Graphs.
Author: vsg-root
Author-email: vsg.dev.tech@gmail.com
Requires-Python: >=3.8,<4.0
Classifier: Programming Language :: Python :: 3
Classifier: Programming Language :: Python :: 3.8
Classifier: Programming Language :: Python :: 3.9
Classifier: Programming Language :: Python :: 3.10
Classifier: Programming Language :: Python :: 3.11
